streamlit_donut/__init__.py
streamlit_donut/streamlit_donut.py
streamlit_donut-0.1.6.dist-info/LICENSE
streamlit_donut-0.1.6.dist-info/METADATA
streamlit_donut-0.1.6.dist-info/WHEEL
streamlit_donut-0.1.6.dist-info/top_level.txt
streamlit_donut-0.1.6.dist-info/RECORD
