Metadata-Version: 2.1
Name: streamlit-donut
Version: 0.1.6
Summary: A Streamlit component for rendering donut metrics/visuals
Home-page: https://github.com/benson-nderitu/streamlit-donut
Author: Benson Nderitu
Author-email: bent25066@gmail.com
Classifier: Programming Language :: Python :: 3
Classifier: License :: OSI Approved :: MIT License
Classifier: Operating System :: OS Independent
Requires-Python: >=3.6
License-File: LICENSE
Requires-Dist: streamlit
Requires-Dist: numpy
